{
  "mappings": [
    {
      "logicType": "SYS.BLL.IRegionLogic",
      "implementationType": "SYS.BLL.RegionLogic"
    },
    {
      "logicType": "SYS.BLL.Domain.GAIA.IGAIALogic",
      "implementationType": "SYS.BLL.Domain.GAIA.GAIALogic"
    },
    {
      "logicType": "SYS.BLL.Domain.Line.ILineBotLogic",
      "implementationType": "SYS.BLL.Domain.Line.LineBotLogic"
    },
    {
      "logicType": "SYS.BLL.Domain.Line.ILineBotReplyLogic",
      "implementationType": "SYS.BLL.Domain.Line.LineBotReplyLogic"
    },
    {
      "logicType": "SYS.BLL.Domain.IDateTimeLogic",
      "implementationType": "SYS.BLL.Domain.DateTimeLogic"
    },
    {
      "logicType": "SYS.BLL.Domain.IFunctionsLogic",
      "implementationType": "SYS.BLL.Domain.FunctionsLogic"
    },
    {
      "logicType": "SYS.BLL.Domain.IGroupsLogic",
      "implementationType": "SYS.BLL.Domain.GroupsLogic"
    },
    {
      "logicType": "SYS.BLL.Domain.IHttpContextStateLogic",
      "implementationType": "SYS.BLL.Domain.HttpContextStateLogic"
    },
    {
      "logicType": "SYS.BLL.Domain.IIniLogic",
      "implementationType": "SYS.BLL.Domain.IniLogic"
    },
    {
      "logicType": "SYS.BLL.Domain.IMailLogic",
      "implementationType": "SYS.BLL.Domain.MailLogic"
    },
    {
      "logicType": "SYS.BLL.Domain.IWebServiceLogic",
      "implementationType": "SYS.BLL.Domain.WebServiceLogic"
    },
    {
      "logicType": "SYS.BLL.Domain.IUsersLogic",
      "implementationType": "SYS.BLL.Domain.UsersLogic"
    }
  ]
}